AUTHORS
LICENSE
MANIFEST.in
README.md
setup.cfg
setup.py
oais_utils/__init__.py
oais_utils/validate.py
oais_utils/version.py
oais_utils.egg-info/PKG-INFO
oais_utils.egg-info/SOURCES.txt
oais_utils.egg-info/dependency_links.txt
oais_utils.egg-info/requires.txt
oais_utils.egg-info/top_level.txt
oais_utils/schemas/sip-schema-d1.json
oais_utils/test/__init__.py
oais_utils/test/test_checksum.py
oais_utils/test/test_validate.py