Metadata-Version: 2.4
Name: oais_utils
Version: 0.3.0
Summary: OAIS utilities
Home-page: https://gitlab.cern.ch/digitalmemory/utils
Author: CERN Digital Memory
Author-email: digitalmemory-support@cern.ch
License: GPLv3
Classifier: License :: OSI Approved :: GNU General Public License v3 (GPLv3)
Classifier: Programming Language :: Python :: 3
Classifier: Programming Language :: Python :: 3.10
Classifier: Programming Language :: Python :: 3.11
License-File: LICENSE
License-File: AUTHORS
Requires-Dist: jsonschema==3.0.2
Requires-Dist: bagit==1.9.0
Dynamic: author
Dynamic: author-email
Dynamic: classifier
Dynamic: description
Dynamic: description-content-type
Dynamic: home-page
Dynamic: license
Dynamic: license-file
Dynamic: requires-dist
Dynamic: summary
